<?xml version="1.0" encoding="utf-8" standalone="yes"?>
<window>
  <id>703</id>
  <defaultcontrol>24</defaultcontrol>
  <allowoverlay>no</allowoverlay>
  <define>#header.label:6022</define>
  <define>#header.hover:hover_settings.png</define>
  <define>#defaultcontrol:24</define>
  <define>#defaultcontrol.onright:9996</define>
  <controls>
    <import>common.settings.xml</import>
    <import>common.time.xml</import>
    <control>
      <type>group</type>
      <description>group element</description>
      <animation effect="fade" time="200" delay="200">windowopen</animation>
      <posX>251</posX>
      <posY>60</posY>
      <width>595</width>
      <height>500</height>
      <layout>StackLayout</layout>
      <control Style="settingsmainbutton">
        <type>button</type>
        <description>MPEG-2 Video Codecs</description>
        <id>24</id>
        <label>6000</label>
        <onup>33</onup>
        <onright>#defaultcontrol.onright</onright>
      </control>
      <control Style="settingsmainbutton">
        <description>H.264 Video Codecs</description>
        <type>button</type>
        <id>29</id>
        <label>6036</label>
        <onright>#defaultcontrol.onright</onright>
      </control>
      <control Style="settingsmainbutton">
        <description>VC1 Video Codecs</description>
        <type>button</type>
        <id>34</id>
        <label>VC1 Video Codecs</label>
        <onright>#defaultcontrol.onright</onright>
      </control>
      <control Style="settingsmainbutton">
        <description>VC1i Video Codecs</description>
        <type>button</type>
        <id>35</id>
        <label>VC1i Video Codecs</label>
        <onright>#defaultcontrol.onright</onright>
      </control>
      <control Style="settingsmainbutton">
        <description>XVID Video Codecs</description>
        <type>button</type>
        <id>36</id>
        <label>XVID Video Codecs</label>
        <onright>#defaultcontrol.onright</onright>
      </control>
      <control Style="settingsmainbutton">
        <description>Audio Codecs</description>
        <type>button</type>
        <id>25</id>
        <label>6001</label>
        <onright>#defaultcontrol.onright</onright>
      </control>
      <control Style="settingsmainbutton">
        <description>AAC Audio Codecs</description>
        <type>button</type>
        <id>30</id>
        <label>6039</label>
        <onright>#defaultcontrol.onright</onright>
      </control>
      <control Style="settingsmainbutton">
        <description>Audio Renderer</description>
        <type>button</type>
        <id>27</id>
        <label>6002</label>
        <onright>#defaultcontrol.onright</onright>
      </control>
      <control Style="settingsmaintogglebutton">
        <description>Source Splitter Selection</description>
        <type>togglebutton</type>
        <id>39</id>
        <label>Source Splitter Selection</label>
        <onright>#defaultcontrol.onright</onright>
      </control>
      <control Style="settingsmainbutton">
        <description>Splitter Source</description>
        <type>button</type>
        <id>38</id>
        <label>Splitter Source</label>
        <onright>#defaultcontrol.onright</onright>
        <disabledcolor>ff909090</disabledcolor>
      </control>
      <control Style="settingsmainbutton">
        <description>Splitter Filesync</description>
        <type>button</type>
        <id>37</id>
        <label>Splitter Filesync</label>
        <onright>#defaultcontrol.onright</onright>
        <disabledcolor>ff909090</disabledcolor>
      </control>
      <control Style="settingsmainbutton">
        <description>Apect Ratio</description>
        <type>button</type>
        <id>28</id>
        <label>6004</label>
        <onright>#defaultcontrol.onright</onright>
      </control>
      <control Style="settingsmaintogglebutton">
        <description>Subtitles On/Off</description>
        <type>togglebutton</type>
        <id>31</id>
        <label>1196</label>
        <onright>#defaultcontrol.onright</onright>
      </control>
      <control Style="settingsmainbutton">
        <description>Subtitle Language</description>
        <type>button</type>
        <id>32</id>
        <label>1029</label>
        <onright>#defaultcontrol.onright</onright>
      </control>
      <control Style="settingsmainbutton">
        <description>Audio Language</description>
        <type>button</type>
        <id>33</id>
        <label>492</label>
        <onright>#defaultcontrol.onright</onright>
        <ondown>24</ondown>
      </control>
      <!--<control Style="settingsmainbutton">
        <description>Skip steps screen button</description>
        <type>button</type>
        <id>21</id>
        <label>6024</label>
        <hyperlink>708</hyperlink>
        <onright>#defaultcontrol.onright</onright>
        <ondown>24</ondown>
      </control>-->
    </control>
  </controls>
</window>
<!--Checksum:4260866e23bc7b73cdd6a8a91308b66d-->