<?xml version="1.0" encoding="utf-8" standalone="yes"?>
<window>
	<controls>
		<control>
			<description>statusbar background</description>
			<type>image</type>
			<id>23458124</id>
			<posX>0</posX>
			<posY>0</posY>
			<width>1920</width>
			<height>80</height>
			<texture>topbar_background.png</texture>
			<visible>no</visible>
		</control>
		<control>
			<description>Start Time Info</description>
			<type>label</type>
			<id>23458125</id>
			<posX>240</posX>
			<posY>20</posY>
			<label>#wmp9PlayerStatus</label>
			<align>right</align>
			<textcolor>ffffffff</textcolor>
			<visible>no</visible>
		</control>
		<control>
			<description>End Time Info</description>
			<type>label</type>
			<id>23458126</id>
			<posX>1680</posX>
			<posY>20</posY>
			<label>font14</label>
			<textcolor>ffffffff</textcolor>
			<visible>no</visible>
		</control>
	</controls>
</window>